{"abilities":[{"ability":{"name":"cute-charm","url":"https://pokeapi.co/api/v2/ability/56/"},"is_hidden":false,"slot":1},{"ability":{"name":"competitive","url":"https://pokeapi.co/api/v2/ability/172/"},"is_hidden":false,"slot":2},{"ability":{"name":"friend-guard","url":"https://pokeapi.co/api/v2/ability/132/"},"is_hidden":true,"slot":3}],"height":3,"id":174,"is_default":true,"moves":["pound","mega-punch","mega-kick","headbutt","body-slam","double-edge","sing","disable","flamethrower","counter","seismic-toss","solar-beam","thunder-wave","dig","toxic","psychic","mimic","screech","double-team","defense-curl","light-screen","reflect","fire-blast","dream-eater","flash","rest","substitute","nightmare","snore","curse","protect","feint-attack","sweet-kiss","mud-slap","zap-cannon","perish-song","icy-wind","detect","endure","charm","rollout","swagger","attract","sleep-talk","heal-bell","return","present","frustration","safeguard","pain-split","hidden-power","rain-dance","sunny-day","psych-up","shadow-ball","uproar","facade","helping-hand","role-play","wish","magic-coat","recycle","endeavor","secret-power","hyper-voice","fake-tears","bounce","covet","shock-wave","water-pulse","gravity","natural-gift","fling","copycat","punishment","last-resort","captivate","grass-knot","round","echoed-voice","heal-pulse","incinerate","work-up","wild-charge","disarming-voice","draining-kiss","misty-terrain","play-rough","confide"],"name":"igglybuff","sprites":{"front_default":"https://raw.githubusercontent.com/PokeAPI/sprites/master/sprites/pokemon/174.png"},"stats":[{"base_stat":90,"effort":1,"stat":{"name":"hp","url":"https://pokeapi.co/api/v2/stat/1/"}},{"base_stat":30,"effort":0,"stat":{"name":"attack","url":"https://pokeapi.co/api/v2/stat/2/"}},{"base_stat":15,"effort":0,"stat":{"name":"defense","url":"https://pokeapi.co/api/v2/stat/3/"}},{"base_stat":40,"effort":0,"stat":{"name":"special-attack","url":"https://pokeapi.co/api/v2/stat/4/"}},{"base_stat":20,"effort":0,"stat":{"name":"special-defense","url":"https://pokeapi.co/api/v2/stat/5/"}},{"base_stat":15,"effort":0,"stat":{"name":"speed","url":"https://pokeapi.co/api/v2/stat/6/"}}],"types":[{"slot":1,"type":{"name":"normal","url":"https://pokeapi.co/api/v2/type/1/"}},{"slot":2,"type":{"name":"fairy","url":"https://pokeapi.co/api/v2/type/18/"}}],"weight":10}