{"abilities":[{"ability":{"name":"suction-cups","url":"https://pokeapi.co/api/v2/ability/21/"},"is_hidden":false,"slot":1},{"ability":{"name":"storm-drain","url":"https://pokeapi.co/api/v2/ability/114/"},"is_hidden":true,"slot":3}],"height":15,"id":346,"is_default":true,"moves":["swords-dance","bind","headbutt","body-slam","wrap","double-edge","acid","hyper-beam","strength","mega-drain","leech-seed","solar-beam","string-shot","earthquake","dig","toxic","mimic","double-team","confuse-ray","constrict","amnesia","flash","rest","rock-slide","substitute","snore","protect","sludge-bomb","mud-slap","sandstorm","giga-drain","endure","swagger","attract","sleep-talk","return","frustration","pain-split","synthesis","hidden-power","sunny-day","psych-up","ancient-power","rock-smash","stockpile","spit-up","swallow","facade","ingrain","secret-power","astonish","rock-tomb","bullet-seed","block","mud-shot","rock-blast","brine","natural-gift","wring-out","gastro-acid","worry-seed","rock-polish","seed-bomb","energy-ball","earth-power","giga-impact","power-whip","stone-edge","captivate","stealth-rock","grass-knot","smack-down","sludge-wave","round","bulldoze","grassy-terrain","confide","infestation","meteor-beam"],"name":"cradily","sprites":{"front_default":"https://raw.githubusercontent.com/PokeAPI/sprites/master/sprites/pokemon/346.png"},"stats":[{"base_stat":86,"effort":0,"stat":{"name":"hp","url":"https://pokeapi.co/api/v2/stat/1/"}},{"base_stat":81,"effort":0,"stat":{"name":"attack","url":"https://pokeapi.co/api/v2/stat/2/"}},{"base_stat":97,"effort":0,"stat":{"name":"defense","url":"https://pokeapi.co/api/v2/stat/3/"}},{"base_stat":81,"effort":0,"stat":{"name":"special-attack","url":"https://pokeapi.co/api/v2/stat/4/"}},{"base_stat":107,"effort":2,"stat":{"name":"special-defense","url":"https://pokeapi.co/api/v2/stat/5/"}},{"base_stat":43,"effort":0,"stat":{"name":"speed","url":"https://pokeapi.co/api/v2/stat/6/"}}],"types":[{"slot":1,"type":{"name":"rock","url":"https://pokeapi.co/api/v2/type/6/"}},{"slot":2,"type":{"name":"grass","url":"https://pokeapi.co/api/v2/type/12/"}}],"weight":604}